LICENSE
MANIFEST.in
README.md
requirements.txt
setup.cfg
setup.py
geolms/__init__.py
geolms/common.py
geolms/geolms.py
geolms.egg-info/PKG-INFO
geolms.egg-info/SOURCES.txt
geolms.egg-info/dependency_links.txt
geolms.egg-info/not-zip-safe
geolms.egg-info/top_level.txt
tests/test_geolms.py