Metadata-Version: 2.1
Name: geolms
Version: 0.0.1
Summary: A python package for mapping
Home-page: https://github.com/masauso2/geolms
Author: Masauso Sakala
Author-email: masauso2@gmail.com
License: MIT license
Keywords: geolms
Classifier: Intended Audience :: Developers
Classifier: License :: OSI Approved :: MIT License
Classifier: Natural Language :: English
Classifier: Programming Language :: Python :: 3
Classifier: Programming Language :: Python :: 3.8
Classifier: Programming Language :: Python :: 3.9
Classifier: Programming Language :: Python :: 3.10
Classifier: Programming Language :: Python :: 3.11
Requires-Python: >=3.8
License-File: LICENSE
